shopty/__init__.py
shopty/__main__.py
shopty/cli.py
shopty/experiments.py
shopty/optimizers.py
shopty/params.py
shopty/supervisors.py
shopty-0.0.3.dist-info/entry_points.txt
shopty-0.0.3.dist-info/LICENSE
shopty-0.0.3.dist-info/WHEEL
shopty-0.0.3.dist-info/METADATA
shopty-0.0.3.dist-info/RECORD
