Metadata-Version: 2.1
Name: shopty
Version: 0.0.3
Summary: shopty is a tool for tuning hyperparameters on your computer or slurm-managed clusters.
Author-email: Thomas Colligan <thomas.colligan@umontana.edu>
Classifier: License :: OSI Approved :: MIT License
Project-URL: Home, https://github.com/colligant/shopty
